<?xml version="1.0" encoding="utf-8"?>
<GameDataBase xmlns:xsi="http://www.w3.org/2001/XMLSchema-instance" xmlns:xsd="http://www.w3.org/2001/XMLSchema">
  <skillDataList>
    <SkillData>
      <cName>决定人物朝向</cName>
      <eName>ChooseDirection</eName>
    </SkillData>
    <SkillData>
      <cName>回避忍术列表</cName>
      <eName>ChooseTrick</eName>
    </SkillData>
    <SkillData>
      <cName>回合结束</cName>
      <eName>EndRound</eName>
    </SkillData>
    <SkillData>
      <cName>第一阶段</cName>
      <eName>FirstAction</eName>
    </SkillData>
    <SkillData>
      <cName>移动</cName>
      <eName>Move</eName>
    </SkillData>
    <SkillData>
      <cName>休息</cName>
      <eName>Rest</eName>
    </SkillData>
    <SkillData>
      <cName>查克拉</cName>
      <eName>RestoreChakra</eName>
    </SkillData>
    <SkillData>
      <cName>第二阶段</cName>
      <eName>SecondAction</eName>
    </SkillData>
    <SkillData>
      <cName>术·忍具</cName>
      <eName>SkillOrToolList</eName>
    </SkillData>
    <SkillData xsi:type="UnitSkillData">
      <cName>分身术</cName>
      <eName>Clone</eName>
      <costMP>2</costMP>
      <costHP>0</costHP>
      <description>放出一个没有实体的分身，分身一旦被攻击立刻消失</description>
      <skillRange>-1</skillRange>
      <hoverRange>0</hoverRange>
      <skillRate>100</skillRate>
      <comboType>cannot</comboType>
      <skillType>effect</skillType>
      <skillClass>ninjutsu</skillClass>
      <rangeType>common</rangeType>
      <animID>2</animID>
    </SkillData>
    <SkillData xsi:type="UnitSkillData">
      <cName>影分身术</cName>
      <eName>ShadowClone</eName>
      <costMP>2</costMP>
      <costHP>0</costHP>
      <description>放出一个有实体的分身，分身被攻击后立即消失</description>
      <skillRange>-1</skillRange>
      <hoverRange>0</hoverRange>
      <skillRate>100</skillRate>
      <comboType>cannot</comboType>
      <skillType>effect</skillType>
      <skillClass>ninjutsu</skillClass>
      <rangeType>common</rangeType>
      <animID>2</animID>
    </SkillData>
    <SkillData xsi:type="UnitSkillData">
      <cName>替身术</cName>
      <eName>Substitute</eName>
      <costMP>3</costMP>
      <costHP>0</costHP>
      <description>利用和圆木等的交换，来改变对方的攻击目标的术</description>
      <skillRange>-1</skillRange>
      <hoverRange>0</hoverRange>
      <skillRate>100</skillRate>
      <comboType>cannot</comboType>
      <skillType>dodge</skillType>
      <skillClass>ninjutsu</skillClass>
      <rangeType>common</rangeType>
      <animID>0</animID>
    </SkillData>
    <SkillData xsi:type="UnitSkillData">
      <cName>瞬身术</cName>
      <eName>Telesport</eName>
      <costMP>1</costMP>
      <costHP>0</costHP>
      <description>用查克拉进行瞬间移动，如此便可穿越障碍物</description>
      <skillRange>-1</skillRange>
      <hoverRange>0</hoverRange>
      <skillRate>100</skillRate>
      <comboType>cannot</comboType>
      <skillType>effect</skillType>
      <skillClass>ninjutsu</skillClass>
      <rangeType>common</rangeType>
      <animID>2</animID>
    </SkillData>
    <SkillData xsi:type="UnitSkillData">
      <cName>变化术</cName>
      <eName>Transfiguration</eName>
      <costMP>2</costMP>
      <costHP>0</costHP>
      <description>变化成同伴的样子后便可进行支援攻击，若变化成对手的样子，就不会被其他的角色攻击</description>
      <skillRange>1</skillRange>
      <hoverRange>0</hoverRange>
      <skillRate>100</skillRate>
      <comboType>cannot</comboType>
      <skillType>effect</skillType>
      <skillClass>ninjutsu</skillClass>
      <rangeType>common</rangeType>
      <animID>2</animID>
    </SkillData>
    <SkillData xsi:type="AttackSkillData">
      <cName>忍者组合拳</cName>
      <eName>NinjaCombo</eName>
      <costMP>0</costMP>
      <costHP>0</costHP>
      <description>基本的体术，攻击相邻格的对手</description>
      <skillRange>1</skillRange>
      <hoverRange>0</hoverRange>
      <skillRate>98</skillRate>
      <comboType>cannot</comboType>
      <skillType>attack</skillType>
      <skillClass>taijutsu</skillClass>
      <rangeType>common</rangeType>
      <animID>1</animID>
      <damageFactor>10</damageFactor>
      <hit>1</hit>
      <extraCrit>0</extraCrit>
      <extraPounce>0</extraPounce>
    </SkillData>
    <SkillData xsi:type="AttackSkillData">
      <cName>手里剑</cName>
      <eName>Shuriken</eName>
      <costMP>0</costMP>
      <costHP>0</costHP>
      <description></description>
      <skillRange>3</skillRange>
      <hoverRange>0</hoverRange>
      <skillRate>98</skillRate>
      <comboType>cannot</comboType>
      <skillType>attack</skillType>
      <skillClass>tool</skillClass>
      <rangeType>straight</rangeType>
      <animID>2</animID>
      <damageFactor>-1</damageFactor>
      <hit>3</hit>
      <extraCrit>0</extraCrit>
      <extraPounce>0</extraPounce>
    </SkillData>
    <SkillData xsi:type="AttackSkillData">
      <cName>影风车</cName>
      <eName>MagicShuriken</eName>
      <costMP>2</costMP>
      <costHP>0</costHP>
      <description>用大型手里剑攻击的术，在装备了风魔手里剑之后便可使用</description>
      <skillRange>-1</skillRange>
      <hoverRange>0</hoverRange>
      <skillRate>98</skillRate>
      <comboType>can</comboType>
      <skillType>attack</skillType>
      <skillClass>ninjutsu</skillClass>
      <rangeType>straight</rangeType>
      <animID>2</animID>
      <damageFactor>50</damageFactor>
      <hit>1</hit>
      <extraCrit>0</extraCrit>
      <extraPounce>0</extraPounce>
    </SkillData>
    <SkillData xsi:type="UnitSkillData">
      <cName>倍化术</cName>
      <eName>Intumescence</eName>
      <costMP>2</costMP>
      <costHP>0</costHP>
      <description>使身体膨大之术，连发的体术的伤害提升</description>
      <skillRange>0</skillRange>
      <hoverRange>0</hoverRange>
      <skillRate>100</skillRate>
      <comboType>must</comboType>
      <skillType>effect</skillType>
      <skillClass>ninjutsu</skillClass>
      <rangeType>common</rangeType>
      <animID>3</animID>
    </SkillData>
    <SkillData xsi:type="UnitSkillData">
      <cName>吃</cName>
      <eName>Eat</eName>
      <costMP>0</costMP>
      <costHP>0</costHP>
      <description>吃零食，恢复体力及查克拉，一场战斗只能使用一次</description>
      <skillRange>0</skillRange>
      <hoverRange>0</hoverRange>
      <skillRate>100</skillRate>
      <comboType>cannot</comboType>
      <skillType>effect</skillType>
      <skillClass>other</skillClass>
      <rangeType>common</rangeType>
      <animID>2</animID>
    </SkillData>
    <SkillData xsi:type="UnitSkillData">
      <cName>倍化术</cName>
      <eName>IntumescenceD</eName>
      <costMP>2</costMP>
      <costHP>0</costHP>
      <description>在对方攻击之前做好准备，膨大后的身体受到的损失为0</description>
      <skillRange>0</skillRange>
      <hoverRange>0</hoverRange>
      <skillRate>100</skillRate>
      <comboType>cannot</comboType>
      <skillType>defence</skillType>
      <skillClass>ninjutsu</skillClass>
      <rangeType>common</rangeType>
      <animID>2</animID>
    </SkillData>
    <SkillData xsi:type="AttackSkillData">
      <cName>肉弹战车</cName>
      <eName>MeatBulletTank</eName>
      <costMP>0</costMP>
      <costHP>50</costHP>
      <description>与“倍化术”连续使用，就可在水平、直线上，进行连发体术的攻击</description>
      <skillRange>5</skillRange>
      <hoverRange>0</hoverRange>
      <skillRate>95</skillRate>
      <comboType>cannot</comboType>
      <skillType>attack</skillType>
      <skillClass>taijutsu</skillClass>
      <rangeType>straight</rangeType>
      <animID>0</animID>
      <damageFactor>7</damageFactor>
      <hit>5</hit>
      <extraCrit>0</extraCrit>
      <extraPounce>0</extraPounce>
    </SkillData>
    <SkillData xsi:type="AttackSkillData">
      <cName>四脚术</cName>
      <eName>BeastAttack</eName>
      <costMP>3</costMP>
      <costHP>0</costHP>
      <description>把查克拉集中于手脚上，像野兽一样攻击对方的术</description>
      <skillRange>3</skillRange>
      <hoverRange>0</hoverRange>
      <skillRate>95</skillRate>
      <comboType>cannot</comboType>
      <skillType>attack</skillType>
      <skillClass>ninjutsu</skillClass>
      <rangeType>straight</rangeType>
      <animID>4</animID>
      <damageFactor>25</damageFactor>
      <hit>1</hit>
      <extraCrit>0</extraCrit>
      <extraPounce>0</extraPounce>
    </SkillData>
    <SkillData xsi:type="AttackSkillData">
      <cName>牙通牙</cName>
      <eName>BeastCombo</eName>
      <costMP>0</costMP>
      <costHP>40</costHP>
      <description>牙和赤丸变化后的兽人分身，在相邻格便可进行的连携攻击</description>
      <skillRange>2</skillRange>
      <hoverRange>1</hoverRange>
      <skillRate>95</skillRate>
      <comboType>cannot</comboType>
      <skillType>attack</skillType>
      <skillClass>taijutsu</skillClass>
      <rangeType>common</rangeType>
      <animID>2</animID>
      <damageFactor>20</damageFactor>
      <hit>2</hit>
      <extraCrit>0</extraCrit>
      <extraPounce>0</extraPounce>
    </SkillData>
    <SkillData xsi:type="UnitSkillData">
      <cName>兽人分身</cName>
      <eName>BeastClone</eName>
      <costMP>2</costMP>
      <costHP>0</costHP>
      <description>由赤丸变化创造出有实体的分身，可以像影分身一样使用</description>
      <skillRange>-1</skillRange>
      <hoverRange>0</hoverRange>
      <skillRate>100</skillRate>
      <comboType>cannot</comboType>
      <skillType>effect</skillType>
      <skillClass>ninjutsu</skillClass>
      <rangeType>common</rangeType>
      <animID>2</animID>
    </SkillData>
    <SkillData xsi:type="AttackSkillData">
      <cName>影子模仿术</cName>
      <eName>ShadowSimulation</eName>
      <costMP>3</costMP>
      <costHP>0</costHP>
      <description>伸长影子使对方不能行动的术，有效期间自己也无法行动</description>
      <skillRange>4</skillRange>
      <hoverRange>1</hoverRange>
      <skillRate>75</skillRate>
      <comboType>cannot</comboType>
      <skillType>effect</skillType>
      <skillClass>ninjutsu</skillClass>
      <rangeType>straight</rangeType>
      <animID>2</animID>
      <damageFactor>0</damageFactor>
      <hit>1</hit>
      <extraCrit>0</extraCrit>
      <extraPounce>0</extraPounce>
    </SkillData>
    <SkillData xsi:type="AttackSkillData">
      <cName>土遁结界·土牢堂无</cName>
      <eName>EarthStyleDorodomuBarrier</eName>
      <costMP>0</costMP>
      <costHP>0</costHP>
      <description>将敌人困在土的结界内，造成伤害并吸取查克拉。</description>
      <skillRange>1</skillRange>
      <hoverRange>3</hoverRange>
      <skillRate>100</skillRate>
      <comboType>cannot</comboType>
      <skillType>attack</skillType>
      <skillClass>ninjutsu</skillClass>
      <rangeType>other</rangeType>
      <animID>2</animID>
      <damageFactor>20</damageFactor>
      <hit>1</hit>
      <extraCrit>0</extraCrit>
      <extraPounce>0</extraPounce>
    </SkillData>
  </skillDataList>
</GameDataBase>