<?xml version="1.0" encoding="utf-8"?>
<Gal xmlns:xsi="http://www.w3.org/2001/XMLSchema-instance" xmlns:xsd="http://www.w3.org/2001/XMLSchema">
  <bcImg>bcImg_03</bcImg>
  <nextScene>Gal</nextScene>
  <voiceOver>
    <string>佐助最终还是选择了离开。</string>
    <string>纲手得知后，第一时间派遣鹿丸集结村中的下忍，执行营救任务。</string>
  </voiceOver>
  <galCons>
    <GalCon>
      <speaker>Shikamaru</speaker>
      <position>Left</position>
      <content>关于作战计划，还有什么别的问题吗？</content>
    </GalCon>
    <GalCon>
      <speaker>Naruto</speaker>
      <position>Right</position>
      <content>……</content>
    </GalCon>
    <GalCon>
      <speaker>Kiba</speaker>
      <position>Right</position>
      <content>……</content>
    </GalCon>
    <GalCon>
      <speaker>Neji</speaker>
      <position>Right</position>
      <content>……</content>
    </GalCon>
    <GalCon>
      <speaker>Choji</speaker>
      <position>Right</position>
      <content>……</content>
    </GalCon>
    <GalCon>
      <position></position>
    </GalCon>
    <GalCon>
      <speaker>Shikamaru</speaker>
      <position>Left</position>
      <content>没有的话，走之前我先把最重要的话说明白。</content>
    </GalCon>
    <GalCon>
      <speaker>Shikamaru</speaker>
      <position>Left</position>
      <content>佐助对我来说，不算是很好的朋友。</content>
    </GalCon>
    <GalCon>
      <speaker>Shikamaru</speaker>
      <position>Left</position>
      <content>我也不是那么喜欢他。</content>
    </GalCon>
    <GalCon>
      <speaker>Naruto</speaker>
      <position>Right</position>
      <content>?!</content>
    </GalCon>
    <GalCon>
      <speaker>Neji</speaker>
      <position>Right</position>
      <content>……</content>
    </GalCon>
    <GalCon>
      <position></position>
    </GalCon>
    <GalCon>
      <speaker>Shikamaru</speaker>
      <position>Left</position>
      <content>但是，佐助也是木叶的忍者。</content>
    </GalCon>
    <GalCon>
      <speaker>Shikamaru</speaker>
      <position>Left</position>
      <content>是我们的同伴。</content>
    </GalCon>
    <GalCon>
      <speaker>Shikamaru</speaker>
      <position>Left</position>
      <content>所以，无论如何，我们都要把他救回来!</content>
    </GalCon>
    <GalCon>
      <speaker>Shikamaru</speaker>
      <position>Left</position>
      <content>这就是咱们木叶的做法。</content>
    </GalCon>
    <GalCon>
      <speaker>Shikamaru</speaker>
      <position>Left</position>
      <content>而且，就算我再怎么怕麻烦……</content>
    </GalCon>
    <GalCon>
      <speaker>Shikamaru</speaker>
      <position>Left</position>
      <content>你们现在的命，就握在我的手中。</content>
    </GalCon>
    <GalCon>
      <speaker>Kiba</speaker>
      <position>Right</position>
      <content>哈，稍微有些中忍的样子了啊！</content>
    </GalCon>
    <GalCon>
      <speaker>Choji</speaker>
      <position>Left</position>
      <content>o(*￣︶￣*)o</content>
    </GalCon>
    <GalCon>
      <speaker>Neji</speaker>
      <position>Right</position>
      <content>那么，大家确认完忍具就出发吧！</content>
    </GalCon>
  </galCons>
</Gal>